mdit_py_i18n/__init__.py
mdit_py_i18n/renderer_i18n.py
mdit_py_i18n/renderer_l10n.py
mdit_py_i18n/utils.py
mdit_py_i18n-0.2.1.dist-info/LICENSES/CC-BY-SA-4.0.txt
mdit_py_i18n-0.2.1.dist-info/LICENSES/LGPL-2.1-or-later.txt
mdit_py_i18n-0.2.1.dist-info/LICENSES/CC0-1.0.txt
mdit_py_i18n-0.2.1.dist-info/WHEEL
mdit_py_i18n-0.2.1.dist-info/METADATA
mdit_py_i18n-0.2.1.dist-info/RECORD
