Metadata-Version: 2.1
Name: mdit-py-i18n
Version: 0.2.1
Summary: Markdown i18n and l10n using markdown-it-py
Home-page: https://github.com/phunh/mdit-py-i18n
License: LGPL-2.1-or-later
Author: Phu Hung Nguyen
Author-email: phuhnguyen@outlook.com
Requires-Python: >=3.8,<4.0
Classifier: Development Status :: 3 - Alpha
Classifier: Intended Audience :: Developers
Classifier: License :: OSI Approved
Classifier: Programming Language :: Python
Classifier: Programming Language :: Python :: 3
Classifier: Programming Language :: Python :: 3.10
Classifier: Programming Language :: Python :: 3.8
Classifier: Programming Language :: Python :: 3.9
Classifier: Topic :: Software Development :: Internationalization
Classifier: Topic :: Software Development :: Libraries
Requires-Dist: Pygments (>=2.16.1,<3.0.0)
Requires-Dist: markdown-it-py[plugins] (>=3.0.0,<4.0.0)
Project-URL: Repository, https://github.com/phunh/mdit-py-i18n
